{
	"basic" :
	{
		"id": "getId",
		"email": "getEmail",
		"name": "getName",
		"phone": "getPhone",
		"profile": "getProfile"
	},
	"full" :
	{
		"id": "getId",
		"email": "getEmail",
		"name": "getName",
		"phone": "getPhone",
		"linkedin": "getLinkedin",
		"github": "getGithub",
		"website": "getWebsite", 
		"avatar": "getAvatar",
		"accounts": "getAccounts:id",
		"profile": "getProfile"
	},
	"set" : {
        "protected": {
	        "email" : "setEmail",
	        "name" : "setName",
		    "phone" : "setPhone",
			"linkedin": "setLinkedin",
			"github": "setGithub",
			"website": "setWebsite", 
		    "avatar": "setAvatar",
		    "password": "setPassword",
			"profile": "setProfile"
		}
    }
}
